src/__init__.py
src/dataset.json
src/oracle.py
oracle_version-0.2.0.dist-info/LICENSE
oracle_version-0.2.0.dist-info/WHEEL
oracle_version-0.2.0.dist-info/METADATA
oracle_version-0.2.0.dist-info/RECORD
