Metadata-Version: 2.1
Name: oracle-version
Version: 0.2.0
Summary: Oracle - until for intresting versions name
License: MIT
Author: Alexander Lavrov
Author-email: egnod@ya.ru
Requires-Python: >=3.7,<4.0
Classifier: License :: OSI Approved :: MIT License
Classifier: Programming Language :: Python :: 3
Classifier: Programming Language :: Python :: 3.7
